Beat_Dude/PIPO.v
module PIPO (
	din,
	clk,
	rst,
	dout
	);
input [15:0] din;
input clk,rst;
output [15:0] dout;
wire [15:0] din;
wire clk,rst;
reg [15:0] dout;
always @(posedge clk or negedge rst) begin
	if(!rst) begin
		dout <= 16'b0;
	end
	else begin
		dout <= din;
	end
end
endmodule

Beat_Dude/Beat_Generator.v
module Beat_Generator (
	clk,    // Clock
	rst,  // Asynchronous reset active low
	X_coordinate, //16 bit input from accelerometer
	Y_coordinate, //16 bit input from accelerometer
	Z_coordinate, //16 bit input from accelerometer
	beat_en, // Output if beat detected
	beat_intensity	 // Output of the beat intensity detected
);
input clk, rst;    // Clock, Asynchronous reset active low
input [15:0] X_coordinate, Y_coordinate, Z_coordinate;//16 bit input from accelerometer
output beat_en; // Output if beat detected
output [1:0] beat_intensity;	 // Output of the beat intensity detected
//--------------------------------------------------------------------------------------------------------
wire [15:0] X_save; //Wire to send one instance of X_coordinate data recieved at clk
wire [15:0] Y_save; //Wire to send one instance of Y_coordinate data recieved at clk
wire [15:0] Z_save; //Wire to send one instance of Z_coordinate data recieved at clk
//parameter [15:0] level_1, level_2, level_3;
reg [1:0] beat_intensity;
reg beat_en;
//--------------------------------------------------------------------------------------------------------
parameter	level_1 = 16'b0000000001100100; //Binary 100 - level to compare difference.
parameter	level_2 = 16'b0000000100101100; //Binary 300 - level to compare difference.
parameter	level_3 = 16'b0000000111110100; //Binary 500 - level to compare difference.


//------------------------------------------Instantiantion of PIPO-------------------------------------------
PIPO u0 (
	.clk (clk),
	.rst (rst),
	.din (X_coordinate),
	.dout (X_save)
	);

PIPO u1 (
	.clk (clk),
	.rst (rst),
	.din (Y_coordinate),
	.dout (Y_save)
	);

PIPO u2 (
	.clk (clk),
	.rst (rst),
	.din (Z_coordinate),
	.dout (Z_save)
	);
//------------------------------------------------Always block for subtraction logic-------------------------
always @(posedge clk or posedge rst) begin
	if (rst) begin
//	X_save <= 16'bZ;
//	Y_save <= 16'bZ;
//	Z_save <= 16'bZ;
	beat_en <= 1'b0;
	beat_intensity <= 2'b00;		// reset		
	end
	else if (X_coordinate - X_save > level_1 && X_coordinate - X_save < level_2  || Y_coordinate - Y_save > level_1 && Y_coordinate - Y_save < level_2 || Z_coordinate - Z_save > level_1 && Z_coordinate - Z_save < level_2) begin
	beat_en <= 1'b1;
	beat_intensity <= 2'b01;	
	end
	else if (X_coordinate - X_save > level_2 && X_coordinate - X_save < level_3 || Y_coordinate - Y_save > level_2 && Y_coordinate - Y_save < level_3 || Z_coordinate - Z_save > level_2 && Z_coordinate - Z_save < level_3) begin
	beat_en <= 1'b1;
	beat_intensity <= 2'b10;	
	end
	else if (X_coordinate - X_save > level_3 || Y_coordinate - Y_save > level_3 || Z_coordinate - Z_save > level_3) begin
	beat_en <= 1'b1;
	beat_intensity <= 2'b11;	
	end
end
endmodule

Beat_Dude/Beat_Generator_TB.v
module Beat_Generator_TB;
	reg clk, rst;
	wire beat_en;
	wire [1:0] Level; // Wire to check output of intensity
	reg [15:0] X_save; //Register to send X_coordinate data at clk
	reg [15:0] Y_save; //Register to send Y_coordinate data at clk
	reg [15:0] Z_save; //Register to send Z_coordinate data at clk

	Beat_Generator u0 (
	.clk(clk),    // Clock
	.rst(rst),  // Asynchronous reset active low
	.X_coordinate (X_save),
	.Y_coordinate (Y_save),
	.Z_coordinate (Z_save),
	.beat_en (beat_en),
	.beat_intensity	(Level)
	);

//initial begin
//	clk = 0;
//	rst = 0;
//	X_save = 16'bZ;
//	Y_save = 16'bZ;
//	Z_save = 16'bZ;
//end
initial begin
	rst = 1'b0;
	clk = 1'b0;
	end

always begin
	#40 clk = ~clk;
	end
initial  begin
	$dumpfile ("Beat_Generator.vcd");
	$dumpvars;
end

initial  begin
	$display("\t\ttime,\tclk,\trst,\tX,\tY,\tZ,\tBeat,\tIntensity");
	$monitor("%d,\t%b,\t%b,\t%d,\t%d,\t%d,\t%b,\t%d,",$time,clk,rst,X_save,Y_save,Z_save,beat_en,Level);
end

initial begin
X_save = 16'b0000000010010110;
Y_save = 16'b0000000000000010;
Z_save = 16'b0000000000000010; // X is 150 i.e Level 1
rst = 1'b0;
#80
X_save = 16'b0000000000000010;
Y_save = 16'b0000000101110010;
Z_save = 16'b0000000000000010; // Y is 370 i.e Level 2
rst = 1'b0;
#80
X_save = 16'b0000000000000010;
Y_save = 16'b0000000000000010;
Z_save = 16'b0000001101000000; // Z is 832 i.e Level 3
rst = 1'b0;
#80
X_save = 16'b0000000010010110; // X is level 1
Y_save = 16'b0000000101110010; // Y is level 2
Z_save = 16'b0000000000000010; // Z is level 1
rst = 1'b0;
#80
X_save = 16'b0000000101110010; // X is level 2
Y_save = 16'b0000001101000000; // Y is level 3
Z_save = 16'b0000000010010110; // Z is level 1
rst = 1'b1; // reset bit is 1
#10
#50  $finish;
end 
endmodule

Beat_Dude/Beat_Generator.vcd
$date
	Tue May 03 02:13:47 2016
$end
$version
	ModelSim Version 10.4a
$end
$timescale
	1ns
$end

$scope module Beat_Generator_TB $end
$var reg 1 ! clk $end
$var reg 1 " rst $end
$var wire 1 # beat_en $end
$var wire 1 $ Level [1] $end
$var wire 1 % Level [0] $end
$var reg 16 & X_save [15:0] $end
$var reg 16 ' Y_save [15:0] $end
$var reg 16 ( Z_save [15:0] $end

$scope module u0 $end
$var parameter 16 ) level_1 $end
$var parameter 16 * level_2 $end
$var parameter 16 + level_3 $end
$var wire 1 , clk $end
$var wire 1 - rst $end
$var wire 1 . X_coordinate [15] $end
$var wire 1 / X_coordinate [14] $end
$var wire 1 0 X_coordinate [13] $end
$var wire 1 1 X_coordinate [12] $end
$var wire 1 2 X_coordinate [11] $end
$var wire 1 3 X_coordinate [10] $end
$var wire 1 4 X_coordinate [9] $end
$var wire 1 5 X_coordinate [8] $end
$var wire 1 6 X_coordinate [7] $end
$var wire 1 7 X_coordinate [6] $end
$var wire 1 8 X_coordinate [5] $end
$var wire 1 9 X_coordinate [4] $end
$var wire 1 : X_coordinate [3] $end
$var wire 1 ; X_coordinate [2] $end
$var wire 1 < X_coordinate [1] $end
$var wire 1 = X_coordinate [0] $end
$var wire 1 > Y_coordinate [15] $end
$var wire 1 ? Y_coordinate [14] $end
$var wire 1 @ Y_coordinate [13] $end
$var wire 1 A Y_coordinate [12] $end
$var wire 1 B Y_coordinate [11] $end
$var wire 1 C Y_coordinate [10] $end
$var wire 1 D Y_coordinate [9] $end
$var wire 1 E Y_coordinate [8] $end
$var wire 1 F Y_coordinate [7] $end
$var wire 1 G Y_coordinate [6] $end
$var wire 1 H Y_coordinate [5] $end
$var wire 1 I Y_coordinate [4] $end
$var wire 1 J Y_coordinate [3] $end
$var wire 1 K Y_coordinate [2] $end
$var wire 1 L Y_coordinate [1] $end
$var wire 1 M Y_coordinate [0] $end
$var wire 1 N Z_coordinate [15] $end
$var wire 1 O Z_coordinate [14] $end
$var wire 1 P Z_coordinate [13] $end
$var wire 1 Q Z_coordinate [12] $end
$var wire 1 R Z_coordinate [11] $end
$var wire 1 S Z_coordinate [10] $end
$var wire 1 T Z_coordinate [9] $end
$var wire 1 U Z_coordinate [8] $end
$var wire 1 V Z_coordinate [7] $end
$var wire 1 W Z_coordinate [6] $end
$var wire 1 X Z_coordinate [5] $end
$var wire 1 Y Z_coordinate [4] $end
$var wire 1 Z Z_coordinate [3] $end
$var wire 1 [ Z_coordinate [2] $end
$var wire 1 \ Z_coordinate [1] $end
$var wire 1 ] Z_coordinate [0] $end
$var reg 1 ^ beat_en $end
$var reg 2 _ beat_intensity [1:0] $end
$var wire 1 ` X_save [15] $end
$var wire 1 a X_save [14] $end
$var wire 1 b X_save [13] $end
$var wire 1 c X_save [12] $end
$var wire 1 d X_save [11] $end
$var wire 1 e X_save [10] $end
$var wire 1 f X_save [9] $end
$var wire 1 g X_save [8] $end
$var wire 1 h X_save [7] $end
$var wire 1 i X_save [6] $end
$var wire 1 j X_save [5] $end
$var wire 1 k X_save [4] $end
$var wire 1 l X_save [3] $end
$var wire 1 m X_save [2] $end
$var wire 1 n X_save [1] $end
$var wire 1 o X_save [0] $end
$var wire 1 p Y_save [15] $end
$var wire 1 q Y_save [14] $end
$var wire 1 r Y_save [13] $end
$var wire 1 s Y_save [12] $end
$var wire 1 t Y_save [11] $end
$var wire 1 u Y_save [10] $end
$var wire 1 v Y_save [9] $end
$var wire 1 w Y_save [8] $end
$var wire 1 x Y_save [7] $end
$var wire 1 y Y_save [6] $end
$var wire 1 z Y_save [5] $end
$var wire 1 { Y_save [4] $end
$var wire 1 | Y_save [3] $end
$var wire 1 } Y_save [2] $end
$var wire 1 ~ Y_save [1] $end
$var wire 1 !! Y_save [0] $end
$var wire 1 "! Z_save [15] $end
$var wire 1 #! Z_save [14] $end
$var wire 1 $! Z_save [13] $end
$var wire 1 %! Z_save [12] $end
$var wire 1 &! Z_save [11] $end
$var wire 1 '! Z_save [10] $end
$var wire 1 (! Z_save [9] $end
$var wire 1 )! Z_save [8] $end
$var wire 1 *! Z_save [7] $end
$var wire 1 +! Z_save [6] $end
$var wire 1 ,! Z_save [5] $end
$var wire 1 -! Z_save [4] $end
$var wire 1 .! Z_save [3] $end
$var wire 1 /! Z_save [2] $end
$var wire 1 0! Z_save [1] $end
$var wire 1 1! Z_save [0] $end

$scope module u0 $end
$var wire 1 . din [15] $end
$var wire 1 / din [14] $end
$var wire 1 0 din [13] $end
$var wire 1 1 din [12] $end
$var wire 1 2 din [11] $end
$var wire 1 3 din [10] $end
$var wire 1 4 din [9] $end
$var wire 1 5 din [8] $end
$var wire 1 6 din [7] $end
$var wire 1 7 din [6] $end
$var wire 1 8 din [5] $end
$var wire 1 9 din [4] $end
$var wire 1 : din [3] $end
$var wire 1 ; din [2] $end
$var wire 1 < din [1] $end
$var wire 1 = din [0] $end
$var wire 1 , clk $end
$var wire 1 - rst $end
$var reg 16 2! dout [15:0] $end
$upscope $end

$scope module u1 $end
$var wire 1 > din [15] $end
$var wire 1 ? din [14] $end
$var wire 1 @ din [13] $end
$var wire 1 A din [12] $end
$var wire 1 B din [11] $end
$var wire 1 C din [10] $end
$var wire 1 D din [9] $end
$var wire 1 E din [8] $end
$var wire 1 F din [7] $end
$var wire 1 G din [6] $end
$var wire 1 H din [5] $end
$var wire 1 I din [4] $end
$var wire 1 J din [3] $end
$var wire 1 K din [2] $end
$var wire 1 L din [1] $end
$var wire 1 M din [0] $end
$var wire 1 , clk $end
$var wire 1 - rst $end
$var reg 16 3! dout [15:0] $end
$upscope $end

$scope module u2 $end
$var wire 1 N din [15] $end
$var wire 1 O din [14] $end
$var wire 1 P din [13] $end
$var wire 1 Q din [12] $end
$var wire 1 R din [11] $end
$var wire 1 S din [10] $end
$var wire 1 T din [9] $end
$var wire 1 U din [8] $end
$var wire 1 V din [7] $end
$var wire 1 W din [6] $end
$var wire 1 X din [5] $end
$var wire 1 Y din [4] $end
$var wire 1 Z din [3] $end
$var wire 1 [ din [2] $end
$var wire 1 \ din [1] $end
$var wire 1 ] din [0] $end
$var wire 1 , clk $end
$var wire 1 - rst $end
$var reg 16 4! dout [15:0] $end
$upscope $end
$upscope $end
$upscope $end
$enddefinitions $end
#0
$dumpvars
0!
0"
b10010110 &
b10 '
b10 (
x^
bx _
b0 2!
b0 3!
b0 4!
b1100100 )
b100101100 *
b111110100 +
x#
x%
x$
0o
0n
0m
0l
0k
0j
0i
0h
0g
0f
0e
0d
0c
0b
0a
0`
0!!
0~
0}
0|
0{
0z
0y
0x
0w
0v
0u
0t
0s
0r
0q
0p
01!
00!
0/!
0.!
0-!
0,!
0+!
0*!
0)!
0(!
0'!
0&!
0%!
0$!
0#!
0"!
0]
1\
0[
0Z
0Y
0X
0W
0V
0U
0T
0S
0R
0Q
0P
0O
0N
0M
1L
0K
0J
0I
0H
0G
0F
0E
0D
0C
0B
0A
0@
0?
0>
0=
1<
1;
0:
19
08
07
16
05
04
03
02
01
00
0/
0.
0-
0,
$end
#40
1!
1,
1^
b1 _
1#
1%
0$
#80
b10 &
b101110010 '
0!
1I
1H
1G
1E
0;
09
06
0,
#120
1!
1,
b10 _
0%
1$
#160
b10 '
b1101000000 (
0!
0\
1W
1U
1T
0I
0H
0G
0E
0,
#200
1!
1,
b11 _
1%
#240
b10010110 &
b101110010 '
b10 (
0!
1\
0W
0U
0T
1I
1H
1G
1E
1;
19
16
0,
#280
1!
1,
b1 _
0$
#320
b101110010 &
b1101000000 '
b10010110 (
1"
0!
1[
1Y
1V
0L
0I
0H
1D
0;
18
17
06
15
1-
0,
0^
b0 _
0#
0%
#360
1!
1,
b101110010 2!
b1101000000 3!
b10010110 4!
10!
1/!
1-!
1*!
1y
1w
1v
1n
1k
1j
1i
1g
